{"_fetched_at": "2026-05-06T18:47:18.185977+00:00", "is_active": false, "seasons": [{"season_id": "1997-98", "year": 1998, "team": "DEN", "gp": 65, "pts": 544.0, "reb": 351.0, "ast": 60.0}, {"season_id": "1998-99", "year": 1999, "team": "BOS", "gp": 50, "pts": 335.0, "reb": 300.0, "ast": 53.0}, {"season_id": "1999-00", "year": 2000, "team": "BOS", "gp": 82, "pts": 541.0, "reb": 410.0, "ast": 63.0}, {"season_id": "2000-01", "year": 2001, "team": "BOS", "gp": 40, "pts": 260.0, "reb": 233.0, "ast": 16.0}, {"season_id": "2001-02", "year": 2002, "team": "BOS", "gp": 74, "pts": 510.0, "reb": 481.0, "ast": 35.0}, {"season_id": "2002-03", "year": 2003, "team": "BOS", "gp": 67, "pts": 487.0, "reb": 433.0, "ast": 49.0}, {"season_id": "2003-04", "year": 2004, "team": "BOS", "gp": 23, "pts": 136.0, "reb": 118.0, "ast": 21.0}, {"season_id": "2003-04", "year": 2004, "team": "CLE", "gp": 50, "pts": 272.0, "reb": 241.0, "ast": 37.0}, {"season_id": "2004-05", "year": 2005, "team": "ORL", "gp": 81, "pts": 394.0, "reb": 452.0, "ast": 42.0}, {"season_id": "2005-06", "year": 2006, "team": "ORL", "gp": 82, "pts": 649.0, "reb": 457.0, "ast": 49.0}, {"season_id": "2006-07", "year": 2007, "team": "ORL", "gp": 66, "pts": 404.0, "reb": 344.0, "ast": 35.0}, {"season_id": "2008-09", "year": 2009, "team": "ORL", "gp": 77, "pts": 372.0, "reb": 278.0, "ast": 31.0}, {"season_id": "2009-10", "year": 2010, "team": "NJN", "gp": 15, "pts": 36.0, "reb": 23.0, "ast": 3.0}, {"season_id": "2010-11", "year": 2011, "team": "PHI", "gp": 38, "pts": 100.0, "reb": 99.0, "ast": 12.0}, {"season_id": "2011-12", "year": 2012, "team": "PHI", "gp": 27, "pts": 42.0, "reb": 67.0, "ast": 16.0}], "draft_round": 1, "draft_pick": 5, "country": "USA"}