{"_fetched_at": "2026-05-06T18:55:19.782143+00:00", "is_active": false, "seasons": [{"season_id": "2016-17", "year": 2017, "team": "MIL", "gp": 75, "pts": 767.0, "reb": 213.0, "ast": 317.0}, {"season_id": "2017-18", "year": 2018, "team": "MIL", "gp": 48, "pts": 625.0, "reb": 156.0, "ast": 152.0}, {"season_id": "2018-19", "year": 2019, "team": "MIL", "gp": 64, "pts": 1001.0, "reb": 288.0, "ast": 205.0}, {"season_id": "2019-20", "year": 2020, "team": "IND", "gp": 54, "pts": 893.0, "reb": 262.0, "ast": 381.0}, {"season_id": "2020-21", "year": 2021, "team": "IND", "gp": 56, "pts": 1186.0, "reb": 294.0, "ast": 329.0}, {"season_id": "2021-22", "year": 2022, "team": "IND", "gp": 36, "pts": 687.0, "reb": 185.0, "ast": 212.0}, {"season_id": "2022-23", "year": 2023, "team": "BOS", "gp": 67, "pts": 1000.0, "reb": 280.0, "ast": 248.0}, {"season_id": "2023-24", "year": 2024, "team": "POR", "gp": 39, "pts": 613.0, "reb": 148.0, "ast": 214.0}, {"season_id": "2024-25", "year": 2025, "team": "WAS", "gp": 24, "pts": 305.0, "reb": 91.0, "ast": 98.0}], "draft_round": 2, "draft_pick": 36, "country": "USA"}