{"_fetched_at": "2026-05-06T19:20:34.310367+00:00", "is_active": true, "seasons": [{"season_id": "2023-24", "year": 2024, "team": "MEM", "gp": 4, "pts": 10.0, "reb": 14.0, "ast": 6.0}, {"season_id": "2023-24", "year": 2024, "team": "DET", "gp": 13, "pts": 91.0, "reb": 46.0, "ast": 10.0}, {"season_id": "2024-25", "year": 2025, "team": "BKN", "gp": 28, "pts": 267.0, "reb": 120.0, "ast": 55.0}, {"season_id": "2025-26", "year": 2026, "team": "NYK", "gp": 5, "pts": 0.0, "reb": 2.0, "ast": 0.0}], "draft_round": null, "draft_pick": null, "country": "United Kingdom"}