{"_fetched_at": "2026-05-06T20:45:47.886220+00:00", "is_active": false, "seasons": [{"season_id": "2006-07", "year": 2007, "team": "CHI", "gp": 71, "pts": 256.0, "reb": 153.0, "ast": 60.0}, {"season_id": "2007-08", "year": 2008, "team": "CHI", "gp": 69, "pts": 464.0, "reb": 255.0, "ast": 129.0}, {"season_id": "2008-09", "year": 2009, "team": "CHI", "gp": 43, "pts": 194.0, "reb": 123.0, "ast": 65.0}, {"season_id": "2008-09", "year": 2009, "team": "OKC", "gp": 23, "pts": 195.0, "reb": 119.0, "ast": 46.0}, {"season_id": "2009-10", "year": 2010, "team": "OKC", "gp": 82, "pts": 489.0, "reb": 387.0, "ast": 145.0}, {"season_id": "2010-11", "year": 2011, "team": "OKC", "gp": 79, "pts": 401.0, "reb": 346.0, "ast": 111.0}, {"season_id": "2011-12", "year": 2012, "team": "OKC", "gp": 42, "pts": 203.0, "reb": 128.0, "ast": 47.0}, {"season_id": "2012-13", "year": 2013, "team": "OKC", "gp": 81, "pts": 613.0, "reb": 317.0, "ast": 125.0}, {"season_id": "2013-14", "year": 2014, "team": "OKC", "gp": 61, "pts": 383.0, "reb": 220.0, "ast": 94.0}, {"season_id": "2014-15", "year": 2015, "team": "ATL", "gp": 52, "pts": 278.0, "reb": 223.0, "ast": 75.0}, {"season_id": "2015-16", "year": 2016, "team": "ATL", "gp": 75, "pts": 480.0, "reb": 334.0, "ast": 107.0}, {"season_id": "2016-17", "year": 2017, "team": "ATL", "gp": 62, "pts": 444.0, "reb": 270.0, "ast": 107.0}, {"season_id": "2017-18", "year": 2018, "team": "UTA", "gp": 38, "pts": 312.0, "reb": 161.0, "ast": 33.0}, {"season_id": "2018-19", "year": 2019, "team": "UTA", "gp": 50, "pts": 190.0, "reb": 123.0, "ast": 27.0}, {"season_id": "2019-20", "year": 2020, "team": "HOU", "gp": 41, "pts": 92.0, "reb": 93.0, "ast": 25.0}], "draft_round": 1, "draft_pick": 13, "country": "Switzerland"}