{"_fetched_at": "2026-05-06T21:03:05.286730+00:00", "is_active": true, "seasons": [{"season_id": "2012-13", "year": 2013, "team": "TOR", "gp": 62, "pts": 554.0, "reb": 372.0, "ast": 45.0}, {"season_id": "2013-14", "year": 2014, "team": "TOR", "gp": 81, "pts": 916.0, "reb": 714.0, "ast": 57.0}, {"season_id": "2014-15", "year": 2015, "team": "TOR", "gp": 80, "pts": 963.0, "reb": 693.0, "ast": 39.0}, {"season_id": "2015-16", "year": 2016, "team": "TOR", "gp": 60, "pts": 768.0, "reb": 547.0, "ast": 42.0}, {"season_id": "2016-17", "year": 2017, "team": "TOR", "gp": 80, "pts": 959.0, "reb": 759.0, "ast": 57.0}, {"season_id": "2017-18", "year": 2018, "team": "TOR", "gp": 77, "pts": 980.0, "reb": 660.0, "ast": 81.0}, {"season_id": "2018-19", "year": 2019, "team": "TOR", "gp": 30, "pts": 384.0, "reb": 216.0, "ast": 29.0}, {"season_id": "2018-19", "year": 2019, "team": "MEM", "gp": 19, "pts": 379.0, "reb": 203.0, "ast": 41.0}, {"season_id": "2019-20", "year": 2020, "team": "MEM", "gp": 70, "pts": 1044.0, "reb": 788.0, "ast": 131.0}, {"season_id": "2020-21", "year": 2021, "team": "MEM", "gp": 62, "pts": 1058.0, "reb": 776.0, "ast": 112.0}, {"season_id": "2021-22", "year": 2022, "team": "NOP", "gp": 74, "pts": 1314.0, "reb": 843.0, "ast": 190.0}, {"season_id": "2022-23", "year": 2023, "team": "NOP", "gp": 79, "pts": 1115.0, "reb": 804.0, "ast": 140.0}, {"season_id": "2023-24", "year": 2024, "team": "NOP", "gp": 82, "pts": 1002.0, "reb": 721.0, "ast": 173.0}, {"season_id": "2024-25", "year": 2025, "team": "WAS", "gp": 49, "pts": 564.0, "reb": 404.0, "ast": 108.0}, {"season_id": "2024-25", "year": 2025, "team": "SAC", "gp": 32, "pts": 279.0, "reb": 223.0, "ast": 56.0}, {"season_id": "2025-26", "year": 2026, "team": "DEN", "gp": 65, "pts": 567.0, "reb": 329.0, "ast": 78.0}], "draft_round": 1, "draft_pick": 5, "country": "Lithuania"}