{"_fetched_at": "2026-05-06T18:55:31.893525+00:00", "is_active": false, "seasons": [{"season_id": "2011-12", "year": 2012, "team": "NJN", "gp": 56, "pts": 708.0, "reb": 200.0, "ast": 131.0}, {"season_id": "2012-13", "year": 2013, "team": "BKN", "gp": 73, "pts": 394.0, "reb": 104.0, "ast": 76.0}, {"season_id": "2013-14", "year": 2014, "team": "BOS", "gp": 10, "pts": 31.0, "reb": 19.0, "ast": 4.0}, {"season_id": "2013-14", "year": 2014, "team": "GSW", "gp": 7, "pts": 13.0, "reb": 5.0, "ast": 0.0}, {"season_id": "2013-14", "year": 2014, "team": "LAL", "gp": 18, "pts": 115.0, "reb": 30.0, "ast": 21.0}, {"season_id": "2017-18", "year": 2018, "team": "MEM", "gp": 7, "pts": 141.0, "reb": 21.0, "ast": 25.0}, {"season_id": "2018-19", "year": 2019, "team": "MEM", "gp": 29, "pts": 190.0, "reb": 45.0, "ast": 25.0}], "draft_round": 1, "draft_pick": 25, "country": "USA"}