{"_fetched_at": "2026-05-06T19:07:48.802830+00:00", "is_active": false, "seasons": [{"season_id": "2013-14", "year": 2014, "team": "POR", "gp": 15, "pts": 33.0, "reb": 9.0, "ast": 6.0}, {"season_id": "2014-15", "year": 2015, "team": "POR", "gp": 51, "pts": 168.0, "reb": 73.0, "ast": 39.0}, {"season_id": "2015-16", "year": 2016, "team": "POR", "gp": 81, "pts": 832.0, "reb": 216.0, "ast": 99.0}, {"season_id": "2016-17", "year": 2017, "team": "POR", "gp": 79, "pts": 845.0, "reb": 226.0, "ast": 94.0}, {"season_id": "2017-18", "year": 2018, "team": "BKN", "gp": 75, "pts": 990.0, "reb": 324.0, "ast": 117.0}, {"season_id": "2018-19", "year": 2019, "team": "BKN", "gp": 43, "pts": 413.0, "reb": 148.0, "ast": 46.0}, {"season_id": "2019-20", "year": 2020, "team": "ATL", "gp": 28, "pts": 143.0, "reb": 65.0, "ast": 28.0}, {"season_id": "2019-20", "year": 2020, "team": "MIN", "gp": 9, "pts": 29.0, "reb": 12.0, "ast": 5.0}], "draft_round": 2, "draft_pick": 31, "country": "USA"}