{"_fetched_at": "2026-05-06T20:20:50.777808+00:00", "is_active": false, "seasons": [{"season_id": "2013-14", "year": 2014, "team": "ATL", "gp": 20, "pts": 76.0, "reb": 52.0, "ast": 7.0}, {"season_id": "2014-15", "year": 2015, "team": "ATL", "gp": 40, "pts": 197.0, "reb": 119.0, "ast": 25.0}, {"season_id": "2015-16", "year": 2016, "team": "ATL", "gp": 60, "pts": 195.0, "reb": 117.0, "ast": 34.0}, {"season_id": "2016-17", "year": 2017, "team": "ATL", "gp": 70, "pts": 435.0, "reb": 240.0, "ast": 95.0}, {"season_id": "2017-18", "year": 2018, "team": "ATL", "gp": 53, "pts": 405.0, "reb": 230.0, "ast": 51.0}, {"season_id": "2018-19", "year": 2019, "team": "PHI", "gp": 47, "pts": 349.0, "reb": 200.0, "ast": 62.0}, {"season_id": "2018-19", "year": 2019, "team": "LAL", "gp": 17, "pts": 100.0, "reb": 44.0, "ast": 14.0}, {"season_id": "2019-20", "year": 2020, "team": "OKC", "gp": 47, "pts": 226.0, "reb": 108.0, "ast": 40.0}, {"season_id": "2020-21", "year": 2021, "team": "OKC", "gp": 35, "pts": 339.0, "reb": 132.0, "ast": 28.0}, {"season_id": "2021-22", "year": 2022, "team": "OKC", "gp": 43, "pts": 344.0, "reb": 129.0, "ast": 22.0}, {"season_id": "2022-23", "year": 2023, "team": "OKC", "gp": 43, "pts": 265.0, "reb": 135.0, "ast": 38.0}, {"season_id": "2022-23", "year": 2023, "team": "BOS", "gp": 20, "pts": 118.0, "reb": 68.0, "ast": 12.0}, {"season_id": "2023-24", "year": 2024, "team": "WAS", "gp": 24, "pts": 95.0, "reb": 75.0, "ast": 22.0}, {"season_id": "2023-24", "year": 2024, "team": "DET", "gp": 13, "pts": 45.0, "reb": 29.0, "ast": 10.0}, {"season_id": "2023-24", "year": 2024, "team": "OKC", "gp": 16, "pts": 17.0, "reb": 21.0, "ast": 4.0}], "draft_round": 2, "draft_pick": 44, "country": "USA"}