{"_fetched_at": "2026-05-06T18:39:18.872275+00:00", "is_active": true, "seasons": [{"season_id": "2013-14", "year": 2014, "team": "OKC", "gp": 81, "pts": 265.0, "reb": 332.0, "ast": 43.0}, {"season_id": "2014-15", "year": 2015, "team": "OKC", "gp": 70, "pts": 537.0, "reb": 523.0, "ast": 66.0}, {"season_id": "2015-16", "year": 2016, "team": "OKC", "gp": 80, "pts": 636.0, "reb": 533.0, "ast": 62.0}, {"season_id": "2016-17", "year": 2017, "team": "OKC", "gp": 80, "pts": 905.0, "reb": 613.0, "ast": 86.0}, {"season_id": "2017-18", "year": 2018, "team": "OKC", "gp": 76, "pts": 1056.0, "reb": 685.0, "ast": 88.0}, {"season_id": "2018-19", "year": 2019, "team": "OKC", "gp": 80, "pts": 1108.0, "reb": 760.0, "ast": 124.0}, {"season_id": "2019-20", "year": 2020, "team": "OKC", "gp": 63, "pts": 684.0, "reb": 583.0, "ast": 146.0}, {"season_id": "2020-21", "year": 2021, "team": "NOP", "gp": 58, "pts": 438.0, "reb": 514.0, "ast": 111.0}, {"season_id": "2021-22", "year": 2022, "team": "MEM", "gp": 76, "pts": 528.0, "reb": 760.0, "ast": 256.0}, {"season_id": "2022-23", "year": 2023, "team": "MEM", "gp": 42, "pts": 361.0, "reb": 485.0, "ast": 97.0}, {"season_id": "2024-25", "year": 2025, "team": "HOU", "gp": 58, "pts": 225.0, "reb": 327.0, "ast": 66.0}, {"season_id": "2025-26", "year": 2026, "team": "HOU", "gp": 32, "pts": 187.0, "reb": 276.0, "ast": 48.0}], "draft_round": 1, "draft_pick": 12, "country": "New Zealand"}