{"_fetched_at": "2026-05-06T19:00:15.504879+00:00", "is_active": false, "seasons": [{"season_id": "2000-01", "year": 2001, "team": "DET", "gp": 15, "pts": 31.0, "reb": 23.0, "ast": 3.0}, {"season_id": "2001-02", "year": 2002, "team": "DET", "gp": 8, "pts": 17.0, "reb": 6.0, "ast": 2.0}, {"season_id": "2002-03", "year": 2003, "team": "WAS", "gp": 5, "pts": 4.0, "reb": 5.0, "ast": 1.0}, {"season_id": "2003-04", "year": 2004, "team": "GSW", "gp": 76, "pts": 733.0, "reb": 317.0, "ast": 103.0}, {"season_id": "2004-05", "year": 2005, "team": "MEM", "gp": 58, "pts": 522.0, "reb": 225.0, "ast": 114.0}, {"season_id": "2005-06", "year": 2006, "team": "MEM", "gp": 36, "pts": 124.0, "reb": 55.0, "ast": 33.0}, {"season_id": "2006-07", "year": 2007, "team": "MEM", "gp": 28, "pts": 127.0, "reb": 59.0, "ast": 31.0}, {"season_id": "2007-08", "year": 2008, "team": "MEM", "gp": 37, "pts": 124.0, "reb": 96.0, "ast": 22.0}, {"season_id": "2008-09", "year": 2009, "team": "MIN", "gp": 64, "pts": 190.0, "reb": 142.0, "ast": 76.0}, {"season_id": "2009-10", "year": 2010, "team": "MIN", "gp": 29, "pts": 48.0, "reb": 29.0, "ast": 24.0}, {"season_id": "2010-11", "year": 2011, "team": "DAL", "gp": 56, "pts": 145.0, "reb": 59.0, "ast": 40.0}, {"season_id": "2011-12", "year": 2012, "team": "DAL", "gp": 44, "pts": 43.0, "reb": 34.0, "ast": 16.0}], "draft_round": 2, "draft_pick": 44, "country": "USA"}