{"_fetched_at": "2026-05-06T20:22:59.545154+00:00", "is_active": false, "seasons": [{"season_id": "1986-87", "year": 1987, "team": "CLE", "gp": 59, "pts": 293.0, "reb": 70.0, "ast": 27.0}, {"season_id": "1987-88", "year": 1988, "team": "NYK", "gp": 77, "pts": 773.0, "reb": 159.0, "ast": 62.0}, {"season_id": "1988-89", "year": 1989, "team": "NYK", "gp": 81, "pts": 1293.0, "reb": 206.0, "ast": 162.0}, {"season_id": "1989-90", "year": 1990, "team": "NYK", "gp": 80, "pts": 1032.0, "reb": 191.0, "ast": 180.0}, {"season_id": "1990-91", "year": 1991, "team": "CHH", "gp": 81, "pts": 1371.0, "reb": 254.0, "ast": 188.0}, {"season_id": "1991-92", "year": 1992, "team": "CHH", "gp": 55, "pts": 839.0, "reb": 179.0, "ast": 146.0}, {"season_id": "1992-93", "year": 1993, "team": "CHH", "gp": 64, "pts": 764.0, "reb": 143.0, "ast": 117.0}, {"season_id": "1993-94", "year": 1994, "team": "CHH", "gp": 18, "pts": 234.0, "reb": 58.0, "ast": 29.0}, {"season_id": "1993-94", "year": 1994, "team": "NJN", "gp": 63, "pts": 598.0, "reb": 122.0, "ast": 43.0}, {"season_id": "1994-95", "year": 1995, "team": "MIL", "gp": 82, "pts": 634.0, "reb": 173.0, "ast": 91.0}, {"season_id": "1995-96", "year": 1996, "team": "MIL", "gp": 82, "pts": 889.0, "reb": 200.0, "ast": 154.0}, {"season_id": "1996-97", "year": 1997, "team": "MIL", "gp": 82, "pts": 715.0, "reb": 186.0, "ast": 116.0}, {"season_id": "1997-98", "year": 1998, "team": "DEN", "gp": 74, "pts": 1089.0, "reb": 141.0, "ast": 138.0}, {"season_id": "1998-99", "year": 1999, "team": "CLE", "gp": 50, "pts": 303.0, "reb": 75.0, "ast": 41.0}, {"season_id": "1999-00", "year": 2000, "team": "NJN", "gp": 82, "pts": 820.0, "reb": 154.0, "ast": 65.0}, {"season_id": "2000-01", "year": 2001, "team": "NJN", "gp": 82, "pts": 895.0, "reb": 176.0, "ast": 115.0}, {"season_id": "2001-02", "year": 2002, "team": "DAL", "gp": 47, "pts": 198.0, "reb": 49.0, "ast": 14.0}], "draft_round": 2, "draft_pick": 29, "country": "USA"}