{"_fetched_at": "2026-05-06T21:16:25.763691+00:00", "is_active": false, "seasons": [{"season_id": "2004-05", "year": 2005, "team": "MIA", "gp": 3, "pts": 7.0, "reb": 1.0, "ast": 3.0}, {"season_id": "2005-06", "year": 2006, "team": "MIA", "gp": 20, "pts": 58.0, "reb": 32.0, "ast": 8.0}, {"season_id": "2006-07", "year": 2007, "team": "MIA", "gp": 66, "pts": 393.0, "reb": 272.0, "ast": 95.0}, {"season_id": "2007-08", "year": 2008, "team": "MIA", "gp": 44, "pts": 347.0, "reb": 220.0, "ast": 60.0}, {"season_id": "2008-09", "year": 2009, "team": "MIA", "gp": 6, "pts": 18.0, "reb": 20.0, "ast": 2.0}, {"season_id": "2009-10", "year": 2010, "team": "MIA", "gp": 72, "pts": 510.0, "reb": 235.0, "ast": 91.0}, {"season_id": "2010-11", "year": 2011, "team": "GSW", "gp": 82, "pts": 1344.0, "reb": 431.0, "ast": 242.0}, {"season_id": "2011-12", "year": 2012, "team": "GSW", "gp": 61, "pts": 629.0, "reb": 278.0, "ast": 94.0}, {"season_id": "2012-13", "year": 2013, "team": "PHI", "gp": 79, "pts": 729.0, "reb": 302.0, "ast": 150.0}, {"season_id": "2013-14", "year": 2014, "team": "POR", "gp": 68, "pts": 343.0, "reb": 191.0, "ast": 64.0}, {"season_id": "2014-15", "year": 2015, "team": "POR", "gp": 48, "pts": 219.0, "reb": 111.0, "ast": 41.0}], "draft_round": 1, "draft_pick": 19, "country": "USA"}