{"_fetched_at": "2026-05-06T18:58:55.165986+00:00", "is_active": false, "seasons": [{"season_id": "1993-94", "year": 1994, "team": "WAS", "gp": 75, "pts": 518.0, "reb": 225.0, "ast": 77.0}, {"season_id": "1994-95", "year": 1995, "team": "WAS", "gp": 76, "pts": 597.0, "reb": 170.0, "ast": 91.0}, {"season_id": "1995-96", "year": 1996, "team": "WAS", "gp": 61, "pts": 237.0, "reb": 118.0, "ast": 67.0}, {"season_id": "1996-97", "year": 1997, "team": "POR", "gp": 49, "pts": 148.0, "reb": 53.0, "ast": 30.0}, {"season_id": "1997-98", "year": 1998, "team": "CLE", "gp": 18, "pts": 37.0, "reb": 22.0, "ast": 18.0}, {"season_id": "1998-99", "year": 1999, "team": "CLE", "gp": 31, "pts": 168.0, "reb": 44.0, "ast": 22.0}, {"season_id": "2001-02", "year": 2002, "team": "POR", "gp": 11, "pts": 29.0, "reb": 14.0, "ast": 5.0}, {"season_id": "2003-04", "year": 2004, "team": "WAS", "gp": 41, "pts": 134.0, "reb": 71.0, "ast": 32.0}], "draft_round": null, "draft_pick": null, "country": "USA"}