{"_fetched_at": "2026-05-06T18:59:11.222395+00:00", "is_active": false, "seasons": [{"season_id": "1978-79", "year": 1979, "team": "PHX", "gp": 43, "pts": 291.0, "reb": 97.0, "ast": 61.0}, {"season_id": "1978-79", "year": 1979, "team": "NOJ", "gp": 36, "pts": 189.0, "reb": 94.0, "ast": 43.0}, {"season_id": "1979-80", "year": 1980, "team": "LAL", "gp": 32, "pts": 63.0, "reb": 27.0, "ast": 13.0}, {"season_id": "1980-81", "year": 1981, "team": "DAL", "gp": 72, "pts": 561.0, "reb": 177.0, "ast": 113.0}, {"season_id": "1982-83", "year": 1983, "team": "IND", "gp": 80, "pts": 391.0, "reb": 191.0, "ast": 179.0}], "draft_round": 1, "draft_pick": 19, "country": "USA"}