{"_fetched_at": "2026-05-06T19:03:32.984318+00:00", "is_active": false, "seasons": [{"season_id": "1966-67", "year": 1967, "team": "LAL", "gp": 76, "pts": 798.0, "reb": 218.0, "ast": 205.0}, {"season_id": "1967-68", "year": 1968, "team": "LAL", "gp": 81, "pts": 1612.0, "reb": 342.0, "ast": 353.0}, {"season_id": "1968-69", "year": 1969, "team": "PHL", "gp": 82, "pts": 1107.0, "reb": 265.0, "ast": 296.0}, {"season_id": "1969-70", "year": 1970, "team": "PHL", "gp": 76, "pts": 1499.0, "reb": 301.0, "ast": 380.0}, {"season_id": "1970-71", "year": 1971, "team": "PHL", "gp": 82, "pts": 1746.0, "reb": 391.0, "ast": 440.0}, {"season_id": "1971-72", "year": 1972, "team": "BLT", "gp": 76, "pts": 1909.0, "reb": 265.0, "ast": 606.0}, {"season_id": "1971-72", "year": 1972, "team": "PHL", "gp": 1, "pts": 29.0, "reb": 3.0, "ast": 7.0}, {"season_id": "1972-73", "year": 1973, "team": "BLT", "gp": 39, "pts": 715.0, "reb": 129.0, "ast": 275.0}, {"season_id": "1973-74", "year": 1974, "team": "CAP", "gp": 56, "pts": 733.0, "reb": 141.0, "ast": 285.0}, {"season_id": "1974-75", "year": 1975, "team": "SEA", "gp": 77, "pts": 1071.0, "reb": 235.0, "ast": 433.0}, {"season_id": "1975-76", "year": 1976, "team": "DET", "gp": 79, "pts": 600.0, "reb": 137.0, "ast": 218.0}], "draft_round": 4, "draft_pick": 37, "country": "USA"}