{"_fetched_at": "2026-05-06T19:13:44.828893+00:00", "is_active": false, "seasons": [{"season_id": "1973-74", "year": 1974, "team": "GOS", "gp": 66, "pts": 281.0, "reb": 339.0, "ast": 54.0}, {"season_id": "1974-75", "year": 1975, "team": "GOS", "gp": 80, "pts": 614.0, "reb": 550.0, "ast": 125.0}, {"season_id": "1975-76", "year": 1976, "team": "GOS", "gp": 79, "pts": 502.0, "reb": 349.0, "ast": 83.0}, {"season_id": "1976-77", "year": 1977, "team": "GOS", "gp": 49, "pts": 361.0, "reb": 240.0, "ast": 63.0}, {"season_id": "1977-78", "year": 1978, "team": "GOS", "gp": 22, "pts": 136.0, "reb": 49.0, "ast": 11.0}, {"season_id": "1977-78", "year": 1978, "team": "CHI", "gp": 25, "pts": 68.0, "reb": 48.0, "ast": 10.0}], "draft_round": 2, "draft_pick": 29, "country": "USA"}