{"_fetched_at": "2026-05-06T20:05:47.239046+00:00", "is_active": false, "seasons": [{"season_id": "1976-77", "year": 1977, "team": "BUF", "gp": 2, "pts": 0.0, "reb": 1.0, "ast": 0.0}, {"season_id": "1976-77", "year": 1977, "team": "HOU", "gp": 80, "pts": 1083.0, "reb": 1071.0, "ast": 89.0}, {"season_id": "1977-78", "year": 1978, "team": "HOU", "gp": 59, "pts": 1144.0, "reb": 886.0, "ast": 31.0}, {"season_id": "1978-79", "year": 1979, "team": "HOU", "gp": 82, "pts": 2031.0, "reb": 1444.0, "ast": 147.0}, {"season_id": "1979-80", "year": 1980, "team": "HOU", "gp": 82, "pts": 2119.0, "reb": 1190.0, "ast": 147.0}, {"season_id": "1980-81", "year": 1981, "team": "HOU", "gp": 80, "pts": 2222.0, "reb": 1180.0, "ast": 141.0}, {"season_id": "1981-82", "year": 1982, "team": "HOU", "gp": 81, "pts": 2520.0, "reb": 1188.0, "ast": 142.0}, {"season_id": "1982-83", "year": 1983, "team": "PHL", "gp": 78, "pts": 1908.0, "reb": 1194.0, "ast": 101.0}, {"season_id": "1983-84", "year": 1984, "team": "PHL", "gp": 71, "pts": 1609.0, "reb": 950.0, "ast": 96.0}, {"season_id": "1984-85", "year": 1985, "team": "PHL", "gp": 79, "pts": 1941.0, "reb": 1031.0, "ast": 130.0}, {"season_id": "1985-86", "year": 1986, "team": "PHL", "gp": 74, "pts": 1759.0, "reb": 872.0, "ast": 90.0}, {"season_id": "1986-87", "year": 1987, "team": "WAS", "gp": 73, "pts": 1760.0, "reb": 824.0, "ast": 120.0}, {"season_id": "1987-88", "year": 1988, "team": "WAS", "gp": 79, "pts": 1607.0, "reb": 884.0, "ast": 112.0}, {"season_id": "1988-89", "year": 1989, "team": "ATL", "gp": 81, "pts": 1637.0, "reb": 956.0, "ast": 112.0}, {"season_id": "1989-90", "year": 1990, "team": "ATL", "gp": 81, "pts": 1528.0, "reb": 812.0, "ast": 130.0}, {"season_id": "1990-91", "year": 1991, "team": "ATL", "gp": 82, "pts": 869.0, "reb": 667.0, "ast": 68.0}, {"season_id": "1991-92", "year": 1992, "team": "MIL", "gp": 82, "pts": 1279.0, "reb": 744.0, "ast": 93.0}, {"season_id": "1992-93", "year": 1993, "team": "MIL", "gp": 11, "pts": 50.0, "reb": 46.0, "ast": 7.0}, {"season_id": "1993-94", "year": 1994, "team": "PHL", "gp": 55, "pts": 294.0, "reb": 226.0, "ast": 34.0}, {"season_id": "1994-95", "year": 1995, "team": "SAN", "gp": 17, "pts": 49.0, "reb": 46.0, "ast": 6.0}], "draft_round": null, "draft_pick": null, "country": "USA"}