{"_fetched_at": "2026-05-06T20:48:07.285317+00:00", "is_active": false, "seasons": [{"season_id": "1946-47", "year": 1947, "team": "BOS", "gp": 60, "pts": 620.0, "reb": NaN, "ast": 62.0}, {"season_id": "1947-48", "year": 1948, "team": "BAL", "gp": 13, "pts": 138.0, "reb": 0.0, "ast": 7.0}, {"season_id": "1947-48", "year": 1948, "team": "BOS", "gp": 32, "pts": 248.0, "reb": 0.0, "ast": 17.0}, {"season_id": "1948-49", "year": 1949, "team": "BAL", "gp": 60, "pts": 779.0, "reb": NaN, "ast": 116.0}, {"season_id": "1949-50", "year": 1950, "team": "NYK", "gp": 60, "pts": 680.0, "reb": NaN, "ast": 102.0}, {"season_id": "1950-51", "year": 1951, "team": "NYK", "gp": 66, "pts": 604.0, "reb": 426.0, "ast": 117.0}, {"season_id": "1951-52", "year": 1952, "team": "NYK", "gp": 66, "pts": 629.0, "reb": 471.0, "ast": 121.0}, {"season_id": "1952-53", "year": 1953, "team": "NYK", "gp": 65, "pts": 729.0, "reb": 458.0, "ast": 127.0}, {"season_id": "1953-54", "year": 1954, "team": "NYK", "gp": 72, "pts": 720.0, "reb": 484.0, "ast": 128.0}, {"season_id": "1954-55", "year": 1955, "team": "SYR", "gp": 36, "pts": 346.0, "reb": 220.0, "ast": 61.0}, {"season_id": "1955-56", "year": 1956, "team": "ROC", "gp": 68, "pts": 366.0, "reb": 235.0, "ast": 82.0}], "draft_round": null, "draft_pick": null, "country": "USA"}