{"_fetched_at": "2026-05-06T20:51:42.037342+00:00", "is_active": false, "seasons": [{"season_id": "1975-76", "year": 1976, "team": "PHX", "gp": 78, "pts": 718.0, "reb": 259.0, "ast": 215.0}, {"season_id": "1976-77", "year": 1977, "team": "PHX", "gp": 79, "pts": 1071.0, "reb": 234.0, "ast": 238.0}, {"season_id": "1977-78", "year": 1978, "team": "IND", "gp": 79, "pts": 1436.0, "reb": 327.0, "ast": 584.0}, {"season_id": "1978-79", "year": 1979, "team": "IND", "gp": 81, "pts": 1404.0, "reb": 301.0, "ast": 450.0}, {"season_id": "1979-80", "year": 1980, "team": "CHI", "gp": 82, "pts": 1161.0, "reb": 242.0, "ast": 426.0}, {"season_id": "1980-81", "year": 1981, "team": "CHI", "gp": 71, "pts": 958.0, "reb": 144.0, "ast": 284.0}, {"season_id": "1981-82", "year": 1982, "team": "CHI", "gp": 80, "pts": 940.0, "reb": 142.0, "ast": 301.0}, {"season_id": "1982-83", "year": 1983, "team": "WAS", "gp": 41, "pts": 645.0, "reb": 102.0, "ast": 218.0}, {"season_id": "1983-84", "year": 1984, "team": "WAS", "gp": 81, "pts": 1266.0, "reb": 179.0, "ast": 377.0}, {"season_id": "1984-85", "year": 1985, "team": "SEA", "gp": 71, "pts": 700.0, "reb": 103.0, "ast": 252.0}, {"season_id": "1985-86", "year": 1986, "team": "SEA", "gp": 78, "pts": 603.0, "reb": 99.0, "ast": 180.0}], "draft_round": 1, "draft_pick": 16, "country": "USA"}