{"_fetched_at": "2026-05-06T21:07:09.873670+00:00", "is_active": false, "seasons": [{"season_id": "1973-74", "year": 1974, "team": "LAL", "gp": 45, "pts": 172.0, "reb": 147.0, "ast": 19.0}, {"season_id": "1974-75", "year": 1975, "team": "LAL", "gp": 55, "pts": 246.0, "reb": 350.0, "ast": 66.0}, {"season_id": "1975-76", "year": 1976, "team": "LAL", "gp": 36, "pts": 123.0, "reb": 165.0, "ast": 20.0}, {"season_id": "1976-77", "year": 1977, "team": "LAL", "gp": 53, "pts": 514.0, "reb": 492.0, "ast": 48.0}, {"season_id": "1977-78", "year": 1978, "team": "LAL", "gp": 25, "pts": 288.0, "reb": 279.0, "ast": 30.0}, {"season_id": "1977-78", "year": 1978, "team": "BOS", "gp": 32, "pts": 376.0, "reb": 335.0, "ast": 42.0}, {"season_id": "1978-79", "year": 1979, "team": "SDC", "gp": 82, "pts": 927.0, "reb": 800.0, "ast": 125.0}, {"season_id": "1979-80", "year": 1980, "team": "POR", "gp": 80, "pts": 1073.0, "reb": 842.0, "ast": 167.0}, {"season_id": "1980-81", "year": 1981, "team": "POR", "gp": 73, "pts": 831.0, "reb": 686.0, "ast": 149.0}, {"season_id": "1981-82", "year": 1982, "team": "POR", "gp": 20, "pts": 100.0, "reb": 117.0, "ast": 29.0}, {"season_id": "1987-88", "year": 1988, "team": "GOS", "gp": 6, "pts": 16.0, "reb": 19.0, "ast": 0.0}], "draft_round": 1, "draft_pick": 5, "country": "USA"}