{"_fetched_at": "2026-05-06T21:16:03.137732+00:00", "is_active": false, "seasons": [{"season_id": "1989-90", "year": 1990, "team": "ATL", "gp": 6, "pts": 6.0, "reb": 3.0, "ast": 2.0}, {"season_id": "1990-91", "year": 1991, "team": "WAS", "gp": 73, "pts": 581.0, "reb": 242.0, "ast": 353.0}, {"season_id": "1993-94", "year": 1994, "team": "IND", "gp": 65, "pts": 501.0, "reb": 204.0, "ast": 404.0}, {"season_id": "1994-95", "year": 1995, "team": "IND", "gp": 69, "pts": 292.0, "reb": 111.0, "ast": 194.0}, {"season_id": "1995-96", "year": 1996, "team": "IND", "gp": 77, "pts": 279.0, "reb": 124.0, "ast": 213.0}, {"season_id": "1996-97", "year": 1997, "team": "IND", "gp": 4, "pts": 22.0, "reb": 7.0, "ast": 11.0}, {"season_id": "1998-99", "year": 1999, "team": "MIL", "gp": 29, "pts": 200.0, "reb": 102.0, "ast": 172.0}, {"season_id": "1999-00", "year": 2000, "team": "MIL", "gp": 23, "pts": 66.0, "reb": 17.0, "ast": 44.0}, {"season_id": "1999-00", "year": 2000, "team": "TOR", "gp": 13, "pts": 20.0, "reb": 9.0, "ast": 17.0}], "draft_round": 2, "draft_pick": 49, "country": "USA"}